mongo_x_ray-1.2.3.dist-info/licenses/LICENSE
x_ray/__init__.py
x_ray/__main__.py
x_ray/ai.py
x_ray/compatibility_matrix.json
x_ray/config.json
x_ray/utils.py
x_ray/version.py
x_ray/gmd/framework.py
x_ray/healthcheck/__init__.py
x_ray/healthcheck/framework.py
x_ray/healthcheck/issues.py
x_ray/healthcheck/shared.py
x_ray/healthcheck/check_items/__init__.py
x_ray/healthcheck/check_items/base_item.py
x_ray/healthcheck/check_items/build_info_item.py
x_ray/healthcheck/check_items/cluster_item.py
x_ray/healthcheck/check_items/coll_info_item.py
x_ray/healthcheck/check_items/host_info_item.py
x_ray/healthcheck/check_items/index_info_item.py
x_ray/healthcheck/check_items/security_item.py
x_ray/healthcheck/check_items/server_status_item.py
x_ray/healthcheck/check_items/shard_key_item.py
x_ray/healthcheck/rules/__init__.py
x_ray/healthcheck/rules/base_rule.py
x_ray/healthcheck/rules/cache_rule.py
x_ray/healthcheck/rules/connections_rule.py
x_ray/healthcheck/rules/data_size_rule.py
x_ray/healthcheck/rules/fragmentation_rule.py
x_ray/healthcheck/rules/host_info_rule.py
x_ray/healthcheck/rules/index_rule.py
x_ray/healthcheck/rules/numa_rule.py
x_ray/healthcheck/rules/op_latency_rule.py
x_ray/healthcheck/rules/oplog_window_rule.py
x_ray/healthcheck/rules/query_targeting_rule.py
x_ray/healthcheck/rules/rs_config_rule.py
x_ray/healthcheck/rules/rs_status_rule.py
x_ray/healthcheck/rules/security_rule.py
x_ray/healthcheck/rules/shard_balance_rule.py
x_ray/healthcheck/rules/shard_key_rule.py
x_ray/healthcheck/rules/shard_mongos_rule.py
x_ray/healthcheck/rules/version_eol_rule.py
x_ray/log_analysis/__init__.py
x_ray/log_analysis/framework.py
x_ray/log_analysis/query_analyzer.py
x_ray/log_analysis/shared.py
x_ray/log_analysis/log_items/__init__.py
x_ray/log_analysis/log_items/base_item.py
x_ray/log_analysis/log_items/client_meta_item.py
x_ray/log_analysis/log_items/connection_rate_item.py
x_ray/log_analysis/log_items/info_item.py
x_ray/log_analysis/log_items/slow_chart_item.py
x_ray/log_analysis/log_items/slow_rate_item.py
mongo_x_ray-1.2.3.dist-info/METADATA
mongo_x_ray-1.2.3.dist-info/WHEEL
mongo_x_ray-1.2.3.dist-info/entry_points.txt
mongo_x_ray-1.2.3.dist-info/top_level.txt
mongo_x_ray-1.2.3.dist-info/RECORD
