Metadata-Version: 2.4
Name: mongo-x-ray
Version: 1.2.3
Summary: MongoDB diagnostics toolkit with health checks and log analysis
Author: Yaoxing Zhang
License: MIT License
Project-URL: Homepage, https://github.com/mongodb-ps/ce-mongo-x-ray
Project-URL: Repository, https://github.com/mongodb-ps/ce-mongo-x-ray
Project-URL: Issues, https://github.com/mongodb-ps/ce-mongo-x-ray/issues
Keywords: mongodb,diagnostics,healthcheck,log-analysis
Classifier: Development Status :: 4 - Beta
Classifier: Intended Audience :: System Administrators
Classifier: Intended Audience :: Developers
Classifier: License :: OSI Approved :: MIT License
Classifier: Operating System :: OS Independent
Classifier: Programming Language :: Python
Classifier: Programming Language :: Python :: 3
Classifier: Programming Language :: Python :: 3.9
Classifier: Programming Language :: Python :: 3.10
Classifier: Programming Language :: Python :: 3.11
Classifier: Programming Language :: Python :: 3.12
Classifier: Topic :: Database
Classifier: Topic :: System :: Monitoring
Requires-Python: <4,>=3.9
License-File: LICENSE
Requires-Dist: pymongo==4.15.4
Requires-Dist: Jinja2==3.1.6
Requires-Dist: Markdown==3.9
Requires-Dist: MarkupSafe==3.0.3
Requires-Dist: packaging==25
Requires-Dist: Pygments==2.19.2
Requires-Dist: PyYAML==6.0.3
Requires-Dist: requests==2.32.5
Requires-Dist: urllib3==2.5.0
Requires-Dist: openai==2.8.1
Requires-Dist: httpx==0.28.1
Requires-Dist: httpcore==1.0.9
Requires-Dist: h11==0.16.0
Requires-Dist: certifi==2025.11.12
Requires-Dist: idna==3.11
Requires-Dist: sniffio==1.3.1
Requires-Dist: anyio==4.11.0
Provides-Extra: dev
Requires-Dist: black==25.11.0; extra == "dev"
Requires-Dist: pylint==3.3.9; extra == "dev"
Requires-Dist: flake8==7.3.0; extra == "dev"
Requires-Dist: pytest==8.4.2; extra == "dev"
Requires-Dist: pluggy==1.6.0; extra == "dev"
Requires-Dist: iniconfig==2.1.0; extra == "dev"
Requires-Dist: tomli==2.3.0; extra == "dev"
Requires-Dist: pyinstaller==6.17.0; extra == "dev"
Requires-Dist: pyinstaller-hooks-contrib==2025.10; extra == "dev"
Requires-Dist: macholib==1.16.4; extra == "dev"
Requires-Dist: altgraph==0.17.5; extra == "dev"
Provides-Extra: ai
Requires-Dist: torch==2.8.0; extra == "ai"
Requires-Dist: torchvision==0.23.0; extra == "ai"
Requires-Dist: transformers==4.57.3; extra == "ai"
Requires-Dist: accelerate==1.10.1; extra == "ai"
Requires-Dist: bitsandbytes==0.42.0; extra == "ai"
Requires-Dist: huggingface-hub==0.36.0; extra == "ai"
Requires-Dist: safetensors==0.7.0; extra == "ai"
Requires-Dist: tokenizers==0.22.1; extra == "ai"
Requires-Dist: filelock==3.19.1; extra == "ai"
Requires-Dist: fsspec==2025.10.0; extra == "ai"
Requires-Dist: hf-xet==1.2.0; extra == "ai"
Requires-Dist: numpy==2.0.2; extra == "ai"
Requires-Dist: scipy==1.13.1; extra == "ai"
Requires-Dist: pillow==11.3.0; extra == "ai"
Requires-Dist: regex==2025.11.3; extra == "ai"
Requires-Dist: tqdm==4.67.1; extra == "ai"
Requires-Dist: pydantic==2.12.5; extra == "ai"
Requires-Dist: pydantic_core==2.41.5; extra == "ai"
Requires-Dist: annotated-types==0.7.0; extra == "ai"
Requires-Dist: typing_extensions==4.15.0; extra == "ai"
Requires-Dist: jiter==0.12.0; extra == "ai"
Requires-Dist: psutil==7.1.3; extra == "ai"
Requires-Dist: networkx==3.2.1; extra == "ai"
Requires-Dist: sympy==1.14.0; extra == "ai"
Requires-Dist: mpmath==1.3.0; extra == "ai"
Requires-Dist: distro==1.9.0; extra == "ai"
Requires-Dist: dnspython==2.7.0; extra == "ai"
Requires-Dist: charset-normalizer==3.4.4; extra == "ai"
Requires-Dist: exceptiongroup==1.3.1; extra == "ai"
Requires-Dist: importlib_metadata==8.7.0; extra == "ai"
Requires-Dist: typing-inspection==0.4.2; extra == "ai"
Requires-Dist: zipp==3.23.0; extra == "ai"
Dynamic: license-file
